{
  "amazing_sad_song": {
    "category" : "music",
    "sounds": [{
        "name": "survival_remastered:music/game/amazing_sad_song",
        "stream": true
      }
    ]
	"randUntilNextSong" : 500,
	"priority": 0,
	"dimension": "minecraft:overworld",
  },
  "estavius": {
    "category" : "music",
    "sounds": [{
        "name": "survival_remastered:music/game/estavius",
        "stream": true
      }
    ]
	"randUntilNextSong" : 500,
	"priority": 0,
	"dimension": "minecraft:overworld",
  },
  "killer": {
    "category" : "music",
    "sounds": [{
        "name": "survival_remastered:music/game/killer",
        "stream": true
      }
    ]
	"randUntilNextSong": 500,
	"priority": 0,
	"dimension": "minecraft:overworld",
  },
  "megalovania": {
    "category" : "music",
    "sounds": [{
        "name": "survival_remastered:music/game/megalovania",
        "stream": true
      }
    ]
	"randUntilNextSong": 500,
	"priority": 0,
	"dimension": "minecraft:overworld",
  },
  "the_lord_of_the_ring": {
    "category" : "music",
    "sounds": [{
        "name": "survival_remastered:music/game/the_lord_of_the_ring",
        "stream": true
      }
    ]
	"randUntilNextSong": 500,
	"priority": 0,
	"dimension": "minecraft:overworld",
  },
  "try": {
    "category" : "music",
    "sounds": [{
        "name": "survival_remastered:music/game/try",
        "stream": true
      }
    ]
	"randUntilNextSong": 500,
	"priority": 0,
	"dimension": "minecraft:overworld",
  },
  "ambient": {
    "category" : "music",
    "sounds": [{
		"name": "survival_remastered:music/game/ambient",
		"stream": true
	  }
	]
	"randUntilNextSong": 500,
	"priority": 0,
	"dimension": "minecraft:overworld",
  },
  "olympus": {
    "category" : "music",
	"sounds": [{
		"name": "survival_remastered:music/nether/olympus",
		"stream": true
	  }
	]
	"randUntilNextSong": 500,
	"priority": 0
	"dimension": "minecraft:the_nether",
  },
  "flight_hymn": {
    "category" : "music",
	"sounds": [{
		"name": "survival_remastered:music/nether/flight_hymn",
		"stream": true
	  }
	]
	"randUntilNextSong": 500,
	"priority": 0
	"dimension": "minecraft:the_nether",
  },
  "hope": {
	"category" : "music",
	"sounds": [{
		"name": "survival_remastered:music/nether/hope",
		"stream": true
	  }
	]
	"randUntilNextSong": 500,
	"priority": 0
	"dimension": "minecraft:the_nether",
  },
  "battle_of_the_dragons": {
	"category" : "music",
	"sounds": [{
		"name": "survival_remastered:music/end/battle_of_the_dragons",
		"stream": true
	  }
	]
	"randUntilNextSong": 500,
	"priority": 0
	"dimension": "minecraft:the_end",
	"playOnDragon": true,
  },
  "knights_of_camelot": {
	"category" : "music",
	"sounds": [{
		"name": "survival_remastered:music/game/knights_of_camelot",
		"stream": true
	  }
	]
	"randUntilNextSong": 500,
	"priority": 0
	"dimension": "minecraft:overworld",
  },
  "draconis": {
	"category" : "music",
	"sounds": [{
		"name": "survival_remastered:music/end/draconis",
		"stream": true
	  }
	]
	"randUntilNextSong": 500,
	"priority": 0
	"dimension": "minecraft:the_end",
	"playOnDragon": true,
  },
  "the_sound_of_light": {
	"category" : "music",
	"sounds": [{
		"name": "survival_remastered:music/game/the_sound_of_light",
		"stream": true
	  }
	]
	"randUntilNextSong": 500,
	"priority": 0
	"dimension": "minecraft:overworld",
  },
  "cinematic_chillhop_main": {
	"category" : "music",
	"sounds": [{
		"name": "survival_remastered:music/game/cinematic_chillhop_main",
		"stream": true
	  }
	]
	"randUntilNextSong": 500,
	"priority": 0
	"dimension": "minecraft:overworld",
  },
  "wet_hands": {
    "category" : "music",
    "sounds": [{
		"name": "survival_remastered:music/game/wet_hands",
		"stream": true
	  }
	]
	"randUntilNextSong": 500,
	"priority": 0
	"dimension": "minecraft:overworld",
  }
}